app_ordering/__init__.py
app_ordering/admin.py
app_ordering/apps.py
app_ordering/helpers.py
app_ordering/models.py
app_ordering/services.py
app_ordering/signals.py
app_ordering/tests.py
app_ordering/views.py
app_ordering/management/__init__.py
app_ordering/management/commands/__init__.py
app_ordering/management/commands/admin_app_sort_models.py
app_ordering/management/commands/admin_app_sync_apps.py
app_ordering/migrations/0001_initial.py
app_ordering/migrations/0002_alter_profile_groups_alter_profile_users.py
app_ordering/migrations/__init__.py
app_ordering/templates/__init__.py
app_ordering/templates/admin/__init__.py
app_ordering/templates/admin/app_list.html
app_ordering/templates/admin/app_ordering/__init__.py
app_ordering/templates/admin/app_ordering/profile/__init__.py
app_ordering/templates/admin/app_ordering/profile/change_list.html
app_ordering/templates/adminsortable2/__init__.py
app_ordering/templates/adminsortable2/edit_inline/__init__.py
app_ordering/templates/adminsortable2/edit_inline/tabular-django-5.2.html
app_ordering-1.9.dist-info/licenses/LICENSE.txt
app_ordering-1.9.dist-info/METADATA
app_ordering-1.9.dist-info/WHEEL
app_ordering-1.9.dist-info/top_level.txt
app_ordering-1.9.dist-info/RECORD
