Metadata-Version: 2.4
Name: app_ordering
Version: 1.9
Summary: Sorting and toggle visible for Django admin apps
Home-page: https://github.com/kajalagroup/django-admin-app-ordering
Author: Tuan Bach Van
Author-email: tuan@kajala.com
License: MIT licence, see LICENCE.txt
License-File: LICENSE.txt
Requires-Dist: Django>=4.0
Requires-Dist: django-admin-sortable2>=2.2.6
Dynamic: author
Dynamic: author-email
Dynamic: description
Dynamic: description-content-type
Dynamic: home-page
Dynamic: license
Dynamic: license-file
Dynamic: requires-dist
Dynamic: summary
